CHANGELOG.txt
COPYING
README.txt
setup.py
testing/__init__.py
testing/test_bootstrap.py
testing/test_commands.py
testing/test_sync2.py
vadm/TODO.txt
vadm/__init__.py
vadm/cmdline.py
vadm/env.py
vadm/logger.py
vadm/sync.py
vadm/sync2.py
vadm.egg-info/PKG-INFO
vadm.egg-info/SOURCES.txt
vadm.egg-info/dependency_links.txt
vadm.egg-info/requires.txt
vadm.egg-info/top_level.txt
vadm/bin/vadm