Metadata-Version: 1.1
Name: vadm
Version: 0.6.3
Summary: tool for versioning system files and directories
Home-page: http://codespeak.net/vadm
Author: holger krekel, merlinux GmbH
Author-email: holger@merlinux.de
License: GPL V3
Platform: UNKNOWN
Classifier: Development Status :: 5 - Production/Stable
Classifier: Intended Audience :: System Administrators
Classifier: License :: OSI Approved :: GNU General Public License (GPL)
Classifier: Operating System :: POSIX
Classifier: Programming Language :: Python
Classifier: Topic :: System :: Systems Administration
